kanengine/__init__.py
kanengine/abc.py
kanengine/base/__init__.py
kanengine/base/change_detect.py
kanengine/base/detect.py
kanengine/base/lane.py
kanengine/base/lane2.py
kanengine/base/obb_detect.py
kanengine/base/ocr/__init__.py
kanengine/base/ocr/text_angle_cls.py
kanengine/base/ocr/text_det.py
kanengine/base/ocr/text_rec.py
kanengine/base/people_flow.py
kanengine/base/trackers/__init__.py
kanengine/base/trackers/basetrack.py
kanengine/base/trackers/bot_sort.py
kanengine/base/trackers/byte_tracker.py
kanengine/base/trackers/utils/__init__.py
kanengine/base/trackers/utils/gmc.py
kanengine/base/trackers/utils/kalman_filter.py
kanengine/base/trackers/utils/matching.py
kanengine/base/trackers/utils/metrics.py
kanengine/combine/__init__.py
kanengine/combine/accident_detect.py
kanengine/combine/object_tracking.py
kanengine/combine/speed_measure.py
kanengine/feature/__init__.py
kanengine/feature/change_detect.py
kanengine/feature/detect.py
kanengine/feature/lane.py
kanengine/feature/license_plate.py
kanengine/feature/obb_detect.py
kanengine/feature/people_flow.py
kanengine/register.py
kanengine/utils/__init__.py
kanengine/utils/backend.py
kanengine/utils/export.py
kanengine/utils/ops.py
kanengine/utils/plot.py
kanengine/version.py
kanengine-1.4.31.dist-info/METADATA
kanengine-1.4.31.dist-info/WHEEL
kanengine-1.4.31.dist-info/RECORD
