Metadata-Version: 2.1
Name: kanengine
Version: 1.4.31
Summary: algorithm engine
Author: linlinzhao
Author-email: flinzhao@foxemail.com
Requires-Python: >=3.10,<4.0
Classifier: Programming Language :: Python :: 3
Classifier: Programming Language :: Python :: 3.10
Classifier: Programming Language :: Python :: 3.11
Requires-Dist: lap
Requires-Dist: numpy (==1.23.5)
Requires-Dist: onnxruntime-gpu
Requires-Dist: opencv-python (==4.9.0.80)
Requires-Dist: pyclipper
Requires-Dist: pyyaml (==6.0.1)
Requires-Dist: scipy (==1.9.3)
Requires-Dist: shapely (==2.0.3)
Requires-Dist: torch (>=1.11.0)
Requires-Dist: torchvision (>=0.12.0)
